hass_uniocloud/__init__.py
hass_uniocloud/account_link.py
hass_uniocloud/acme.py
hass_uniocloud/auth.py
hass_uniocloud/client.py
hass_uniocloud/cloud_api.py
hass_uniocloud/cloudhooks.py
hass_uniocloud/const.py
hass_uniocloud/google_report_state.py
hass_uniocloud/iot.py
hass_uniocloud/iot_base.py
hass_uniocloud/remote.py
hass_uniocloud/thingtalk.py
hass_uniocloud/utils.py
hass_uniocloud/voice.py
hass_uniocloud-0.1.3.dist-info/LICENSE
hass_uniocloud-0.1.3.dist-info/METADATA
hass_uniocloud-0.1.3.dist-info/WHEEL
hass_uniocloud-0.1.3.dist-info/top_level.txt
hass_uniocloud-0.1.3.dist-info/RECORD
