Metadata-Version: 2.1
Name: hass-uniocloud
Version: 0.1.3
Summary: Home Assistant cloud integration by UNIO Smart Home
Home-page: https://www.uniosmarthome.com
Author: UNIO Smart Home
Author-email: developers@freshminds.com.br
License: GPL v3
Download-URL: https://github.com/uniosmarthome/hass-uniocloud/tarball/0.1.3
Keywords: homeassistant,cloud,unio
Platform: any
Classifier: Intended Audience :: End Users/Desktop
Classifier: Intended Audience :: Developers
Classifier: License :: OSI Approved :: GNU General Public License v3 (GPLv3)
Classifier: Operating System :: OS Independent
Classifier: Topic :: Internet :: Proxy Servers
Classifier: Topic :: Software Development :: Libraries :: Python Modules
Classifier: Development Status :: 5 - Production/Stable
Classifier: Programming Language :: Python :: 3.8
Requires-Dist: pycognito (==0.1.4)
Requires-Dist: snitun (==0.20)
Requires-Dist: acme (==1.9.0)
Requires-Dist: cryptography (<4.0,>=2.8)
Requires-Dist: attrs (<20.4,>=19.3)
Requires-Dist: pytz (>=2019.3)
Requires-Dist: aiohttp (>=3.6.1)
Requires-Dist: atomicwrites (==1.4.0)
